reverseshellserver/README.MD
reverseshellserver/__init__.py
reverseshellserver/requirements.txt
reverseshellserver/thirdparty.json
reverseshellserver-0.11.dist-info/LICENSE.rst
reverseshellserver-0.11.dist-info/METADATA
reverseshellserver-0.11.dist-info/WHEEL
reverseshellserver-0.11.dist-info/top_level.txt
reverseshellserver-0.11.dist-info/RECORD
