Metadata-Version: 2.1
Name: reverseshellserver
Version: 0.11
Summary: Reverse shell SERVER for unbureaucratic server/client connections with file transfer / screenshots
Home-page: https://github.com/hansalemaos/reverseshellserver
Author: Johannes Fischer
Author-email: aulasparticularesdealemaosp@gmail.com
License: MIT
Keywords: network,reverse,shell
Classifier: Development Status :: 4 - Beta
Classifier: Programming Language :: Python :: 3 :: Only
Classifier: Programming Language :: Python :: 3.10
Classifier: Topic :: Software Development :: Libraries :: Python Modules
Classifier: Topic :: Utilities
License-File: LICENSE.rst
Requires-Dist: get-consecutive-filename
Requires-Dist: kthread
Requires-Dist: kthread-sleep
Requires-Dist: mss
Requires-Dist: numpy
Requires-Dist: opencv-python
